[{"id":"7f5adc61-a65f-4979-9827-9fdb30a4f49b","title":"I am new asing","description":"dwa","category":"UX","status":"done","assignedto":null,"timestamp":"1772749054464"},{"id":"bf67f007-0d28-4330-9a8c-6fe560929f1d","title":"Hello man","description":"add asignment","category":"UX","status":"doing","assignedto":"Thianhom Howard (pogs)","timestamp":"1772784227149"},{"id":"0b15a09e-c36e-477f-9457-780ea6d1fc6e","title":"frontend proj","description":"","category":"Frontend","status":"doing","assignedto":null,"timestamp":"1772784297888"}]